README.md
setup.py
XOne_Magic/Xsms.py
XOne_Magic/__init__.py
XOne_Magic.egg-info/PKG-INFO
XOne_Magic.egg-info/SOURCES.txt
XOne_Magic.egg-info/dependency_links.txt
XOne_Magic.egg-info/requires.txt
XOne_Magic.egg-info/top_level.txt