Metadata-Version: 2.1
Name: XOne-Magic
Version: 0.0.1
Summary: XOne_Team library
Home-page: UNKNOWN
Author: Amr Elmenyawy
Author-email: XOne_support@gmail.com
License: UNKNOWN
Keywords: python,Xsms,Xcall,XGmail,XFB,XKwai
Platform: UNKNOWN
Classifier: Development Status :: 1 - Planning
Classifier: Intended Audience :: Developers
Classifier: Programming Language :: Python :: 3
Classifier: Operating System :: Unix
Classifier: Operating System :: MacOS :: MacOS X
Classifier: Operating System :: Microsoft :: Windows
